cuba_weather_owm/__init__.py
cuba_weather_owm/data_providers/__init__.py
cuba_weather_owm/data_providers/sources.py
cuba_weather_owm/data_providers/weather_api_client.py
cuba_weather_owm/models/__init__.py
cuba_weather_owm/models/source_model.py
cuba_weather_owm/models/weather_model.py
cuba_weather_owm/repositories/__init__.py
cuba_weather_owm/repositories/source_repository.py
cuba_weather_owm/repositories/weather_repository.py
cuba_weather_owm/utils/__init__.py
cuba_weather_owm/utils/damerau_levenshtein.py
cuba_weather_owm/utils/exceptions.py
cuba_weather_owm-0.0.8.dist-info/LICENSE
cuba_weather_owm-0.0.8.dist-info/METADATA
cuba_weather_owm-0.0.8.dist-info/WHEEL
cuba_weather_owm-0.0.8.dist-info/top_level.txt
cuba_weather_owm-0.0.8.dist-info/RECORD
