Metadata-Version: 2.1
Name: cuba-weather-owm
Version: 0.0.8
Summary: Python3 client for cuba-weather project using openweathermap
Home-page: https://github.com/cuba-weather/cuba-weather-owm-python
Author: Cuban Open Source Community
License: MIT
Platform: UNKNOWN
Classifier: Programming Language :: Python :: 3
Classifier: License :: OSI Approved :: MIT License
Classifier: Operating System :: OS Independent
Requires-Python: >=3.6
Requires-Dist: cuba-weather-municipality
Requires-Dist: pyowm
